{
  "version": 3,
  "middleware": {
    "/": {
      "files": [
        "server/edge-runtime-webpack.js",
        "server/src/middleware.js"
      ],
      "name": "src/middleware",
      "page": "/",
      "matchers": [
        {
          "regexp": "^(?:\\/(_next\\/data\\/[^/]{1,}))?\\/admin(?:\\/((?:[^\\/#\\?]+?)(?:\\/(?:[^\\/#\\?]+?))*))?(\\.json)?[\\/#\\?]?$",
          "originalSource": "/admin/:path*"
        }
      ],
      "wasm": [],
      "assets": [],
      "env": {
        "__NEXT_BUILD_ID": "8e7gR_g5_aJM5q-FWL-2t",
        "NEXT_SERVER_ACTIONS_ENCRYPTION_KEY": "gSaZpT9yFk9FXDL1xt88n5pFHFSU/6PyQy5jsqGV5qw=",
        "__NEXT_PREVIEW_MODE_ID": "fe4a00f5b8dce0331c0dad3485aa0296",
        "__NEXT_PREVIEW_MODE_ENCRYPTION_KEY": "6d14cf95fe6aa18a203b437d706ae645855ad0db2ba4744750484abd7292ece3",
        "__NEXT_PREVIEW_MODE_SIGNING_KEY": "c1a7ec931f10f3563e370cb038f6f0eb134359ec69a42bc12d70a773d9c94e0f"
      }
    }
  },
  "functions": {},
  "sortedMiddleware": [
    "/"
  ]
}