{"node":{"0015159a5a20fd88532e005cf80f733364020e1142":{"workers":{"app/staking/[name]/page":{"moduleId":"43422","async":false},"app/admin/dashboard/page":{"moduleId":"43422","async":false},"app/admin/dashboard/users/page":{"moduleId":"43422","async":false},"app/contact_us/page":{"moduleId":"82026","async":false}},"layer":{"app/staking/[name]/page":"rsc","app/admin/dashboard/page":"rsc","app/admin/dashboard/users/page":"rsc","app/contact_us/page":"action-browser"}},"40c079be2425937b70780c767fa6eeb6250de9800c":{"workers":{"app/staking/[name]/page":{"moduleId":"43422","async":false},"app/admin/dashboard/page":{"moduleId":"43422","async":false},"app/admin/dashboard/users/page":{"moduleId":"43422","async":false},"app/contact_us/page":{"moduleId":"82026","async":false}},"layer":{"app/staking/[name]/page":"rsc","app/admin/dashboard/page":"rsc","app/admin/dashboard/users/page":"rsc","app/contact_us/page":"action-browser"}}},"edge":{},"encryptionKey":"Yqq7E71/Bn9oVBotHHM/HCJ5tFDVmrAuGBgksTiubio="}